plisio/__init__.py
plisio/_meta.py
plisio/_types.py
plisio/clients/__init__.py
plisio/clients/_base.py
plisio/clients/async_client.py
plisio/clients/client.py
plisio/enums.py
plisio/exceptions.py
plisio/utils.py
python_plisio-2.0.2.dist-info/LICENSE
python_plisio-2.0.2.dist-info/METADATA
python_plisio-2.0.2.dist-info/WHEEL
python_plisio-2.0.2.dist-info/RECORD
