Metadata-Version: 2.1
Name: python-plisio
Version: 2.0.2
Summary: Python SDK for Plisio API.
Home-page: https://amiwrpremium.github.io/python-plisio/
License: MIT
Keywords: plisio,api,sdk,python,payments,crypto,gateway,crypto payment,bitcoin,etherium,blockchain,tron,BSC
Author: amiwrpremium
Author-email: amiwrpremium@gmail.com
Requires-Python: >=3.8.1,<4.0.0
Classifier: Intended Audience :: Developers
Classifier: License :: OSI Approved :: MIT License
Classifier: Operating System :: POSIX :: Linux
Classifier: Programming Language :: Python :: 3
Classifier: Programming Language :: Python :: 3.9
Classifier: Programming Language :: Python :: 3.10
Classifier: Programming Language :: Python :: 3.11
Classifier: Topic :: Software Development :: Libraries :: Python Modules
Classifier: Topic :: Utilities
Requires-Dist: aiohttp (>=3.8.4,<4.0.0)
Requires-Dist: pydantic[email] (>=1.10.8,<2.0.0)
Requires-Dist: requests (>=2.31.0,<3.0.0)
Project-URL: Documentation, https://python-plisio.readthedocs.io/en/latest/
Project-URL: Repository, https://github.com/amiwrpremium/python-plisio
